azureml/__init__.py
azureml/automl/__init__.py
azureml/automl/dnn/__init__.py
azureml/automl/dnn/nlp/__init__.py
azureml/automl/dnn/nlp/classification/__init__.py
azureml/automl/dnn/nlp/classification/common/__init__.py
azureml/automl/dnn/nlp/classification/common/constants.py
azureml/automl/dnn/nlp/classification/inference/__init__.py
azureml/automl/dnn/nlp/classification/inference/multiclass_inferencer.py
azureml/automl/dnn/nlp/classification/inference/multilabel_inferencer.py
azureml/automl/dnn/nlp/classification/io/__init__.py
azureml/automl/dnn/nlp/classification/io/read/__init__.py
azureml/automl/dnn/nlp/classification/io/read/_labeling_data_helper.py
azureml/automl/dnn/nlp/classification/io/read/dataloader.py
azureml/automl/dnn/nlp/classification/io/read/pytorch_dataset_wrapper.py
azureml/automl/dnn/nlp/classification/io/read/read_utils.py
azureml/automl/dnn/nlp/classification/io/write/__init__.py
azureml/automl/dnn/nlp/classification/io/write/save_utils.py
azureml/automl/dnn/nlp/classification/io/write/multiclass/__init__.py
azureml/automl/dnn/nlp/classification/io/write/multiclass/score_script.py
azureml/automl/dnn/nlp/classification/io/write/multilabel/__init__.py
azureml/automl/dnn/nlp/classification/io/write/multilabel/score_script.py
azureml/automl/dnn/nlp/classification/multiclass/__init__.py
azureml/automl/dnn/nlp/classification/multiclass/model_wrapper.py
azureml/automl/dnn/nlp/classification/multiclass/runner.py
azureml/automl/dnn/nlp/classification/multiclass/trainer.py
azureml/automl/dnn/nlp/classification/multiclass/utils.py
azureml/automl/dnn/nlp/classification/multilabel/__init__.py
azureml/automl/dnn/nlp/classification/multilabel/model_wrapper.py
azureml/automl/dnn/nlp/classification/multilabel/runner.py
azureml/automl/dnn/nlp/classification/multilabel/trainer.py
azureml/automl/dnn/nlp/classification/multilabel/utils.py
azureml/automl/dnn/nlp/common/__init__.py
azureml/automl/dnn/nlp/common/_data_utils.py
azureml_automl_dnn_nlp-1.61.0.post1.dist-info/licenses/LICENSE.txt
azureml_automl_dnn_nlp-1.61.0.post1.dist-info/METADATA
azureml_automl_dnn_nlp-1.61.0.post1.dist-info/WHEEL
azureml_automl_dnn_nlp-1.61.0.post1.dist-info/namespace_packages.txt
azureml_automl_dnn_nlp-1.61.0.post1.dist-info/top_level.txt
azureml_automl_dnn_nlp-1.61.0.post1.dist-info/RECORD
