Metadata-Version: 2.4
Name: azureml-automl-dnn-nlp
Version: 1.61.0.post1
Summary: End to end deep learning models for NLP tasks in AutoML.
Home-page: https://docs.microsoft.com/python/api/overview/azure/ml/?view=azure-ml-py
Author: Microsoft Corp
License: Proprietary https://aka.ms/azureml-preview-sdk-license 
Classifier: Intended Audience :: Developers
Classifier: Intended Audience :: Science/Research
Classifier: Programming Language :: Python :: 3.8
Classifier: Programming Language :: Python :: 3.9
Classifier: Programming Language :: Python :: 3.10
Classifier: Programming Language :: Python :: 3.11
Classifier: Topic :: Scientific/Engineering :: Artificial Intelligence
Requires-Python: >=3.8,<3.12
License-File: LICENSE.txt
Requires-Dist: azureml-automl-core~=1.61.0
Requires-Dist: azureml-automl-runtime~=1.61.0
Requires-Dist: azureml-core~=1.61.0
Requires-Dist: azureml-telemetry~=1.61.0
Requires-Dist: azureml-train-automl~=1.61.0
Requires-Dist: dataclasses
Requires-Dist: datasets<=2.16.1,>=1.7.0
Requires-Dist: inference_schema
Requires-Dist: seqeval
Requires-Dist: torch==2.8.0
Requires-Dist: accelerate==1.12.0
Requires-Dist: transformers[sentencepiece,torch]==4.53.0
Dynamic: author
Dynamic: classifier
Dynamic: description
Dynamic: description-content-type
Dynamic: home-page
Dynamic: license
Dynamic: license-file
Dynamic: requires-dist
Dynamic: requires-python
Dynamic: summary
